grimoire/__init__.py
grimoire/feature.py
grimoire/genome.py
grimoire/hmm.py
grimoire/io.py
grimoire/sequence.py
grimoire/toolbox.py
grimoire/test/__init__.py
grimoire/test/test_feature.py
grimoire/test/test_genome.py
grimoire/test/test_hmm.py
grimoire/test/test_io.py
grimoire/test/test_programs.py
grimoire/test/test_sequence.py
grimoire/test/test_toolbox.py
grimoire-0.0.2.dist-info/LICENSE
grimoire-0.0.2.dist-info/METADATA
grimoire-0.0.2.dist-info/WHEEL
grimoire-0.0.2.dist-info/top_level.txt
grimoire-0.0.2.dist-info/RECORD
