Metadata-Version: 2.1
Name: grimoire
Version: 0.0.2
Summary: Biological sequence analysis tools
Home-page: https://github.com/KorfLab/grimoire
Author: Ian Korf
Author-email: ifkorf@gmail.com
License: UNKNOWN
Platform: UNKNOWN
Classifier: Programming Language :: Python :: 3
Classifier: License :: OSI Approved :: MIT License
Classifier: Operating System :: OS Independent
Requires-Python: >=3.6
